pyg/__init__.py
pyg/github.py
pyg/languages.py
pyg/Pygemony.py
pyg/run.py
pyg/utils.py
pygemony-0.4.2.dist-info/DESCRIPTION.rst
pygemony-0.4.2.dist-info/entry_points.txt
pygemony-0.4.2.dist-info/METADATA
pygemony-0.4.2.dist-info/metadata.json
pygemony-0.4.2.dist-info/RECORD
pygemony-0.4.2.dist-info/top_level.txt
pygemony-0.4.2.dist-info/WHEEL
