Metadata-Version: 2.0
Name: pygemony
Version: 0.4.2
Summary: Parse long-forgotten TODO messages from Github Repos and create Issues to resolve.
Home-page: https://github.com/GrappigPanda/pygemony
Author: Ian Lee Clark
Author-email: ian@ianleeclark.com
License: The MIT License (MIT)
Requires-Dist: github3.py (==0.9.5)
Requires-Dist: requests (==2.9.1)
Requires-Dist: mock (==1.3.0)
Requires-Dist: uritemplate.py (==0.3.0)
Requires-Dist: wheel (==0.24.0)
Requires-Dist: nose2 (==0.5.0)
